server/__init__.py
server/server.py
server/config/__init__.py
server/config/settigs.py
server/config/utils.py
server/log/__init__.py
server/log/settings/__init__.py
server/log/settings/client_log_config.py
server/log/settings/decor_log_config.py
server/log/settings/server_log_config.py
server/server_app/__init__.py
server/server_app/core.py
server/server_app/exceptions.py
server/server_app/models.py
server/server_app/server_utils.py
server/server_app/gui/__init__.py
server/server_app/gui/server.py
devChat_server-0.1.0.dist-info/METADATA
devChat_server-0.1.0.dist-info/WHEEL
devChat_server-0.1.0.dist-info/top_level.txt
devChat_server-0.1.0.dist-info/RECORD
